{
  "2026-06-10": {
    "repo_net": 7455.0,
    "bona_outstanding": 54000.0,
    "mlf_net": 49000.0
  },
  "2026-06-11": {
    "repo_net": 9340.0,
    "bona_outstanding": 54000.0,
    "mlf_net": 49000.0
  },
  "2026-06-12": {
    "repo_net": 13270.0,
    "bona_outstanding": 60000.0,
    "mlf_net": 49000.0
  },
  "2026-06-13": {
    "repo_net": 11120.0,
    "bona_outstanding": 60000.0,
    "mlf_net": 49000.0
  },
  "2026-06-15": {
    "repo_net": 15370.0,
    "bona_outstanding": 54000.0,
    "mlf_net": 49000.0
  },
  "2026-06-16": {
    "repo_net": 17680.0,
    "bona_outstanding": 54000.0,
    "mlf_net": 49000.0
  },
  "2026-06-17": {
    "repo_net": 20353.0,
    "bona_outstanding": 54000.0,
    "mlf_net": 49000.0
  },
  "2026-06-18": {
    "repo_net": 21243.0,
    "bona_outstanding": 54000.0,
    "mlf_net": 49000.0
  },
  "2026-06-19": {
    "repo_net": 19358.0,
    "bona_outstanding": 54000.0,
    "mlf_net": 49000.0
  },
  "2026-06-22": {
    "repo_net": 20593.0,
    "bona_outstanding": 54000.0,
    "mlf_net": 49000.0
  },
  "2026-06-23": {
    "repo_net": 21588.0,
    "bona_outstanding": 54000.0,
    "mlf_net": 49000.0
  },
  "2026-06-24": {
    "repo_net": 23718.0,
    "bona_outstanding": 54000.0,
    "mlf_net": 54000.0
  },
  "2026-06-25": {
    "repo_net": 23220.0,
    "bona_outstanding": 54000.0,
    "mlf_net": 54000.0
  },
  "2026-06-26": {
    "repo_net": 23055.0,
    "bona_outstanding": 54000.0,
    "mlf_net": 54000.0
  },
  "2026-06-29": {
    "repo_net": 24630.0,
    "bona_outstanding": 54000.0,
    "mlf_net": 54000.0
  },
  "2026-06-30": {
    "repo_net": 20160.0,
    "bona_outstanding": 54000.0,
    "mlf_net": 54000.0
  },
  "2026-07-01": {
    "repo_net": 15915.0,
    "bona_outstanding": 54000.0,
    "mlf_net": 54000.0
  },
  "2026-07-02": {
    "repo_net": 12175.0,
    "bona_outstanding": 54000.0,
    "mlf_net": 54000.0
  }
}